CHANGES.txt
LICENSE.txt
MANIFEST.in
README.rst
requirements.txt
setup.cfg
setup.py
ircpdb/__init__.py
ircpdb/bot.py
ircpdb/debugger.py
ircpdb/exceptions.py
ircpdb/parse.py
ircpdb/paste_backends.py
ircpdb/utils.py
ircpdb.egg-info/PKG-INFO
ircpdb.egg-info/SOURCES.txt
ircpdb.egg-info/dependency_links.txt
ircpdb.egg-info/requires.txt
ircpdb.egg-info/top_level.txt
ircpdb/django/__init__.py
ircpdb/django/models.py
ircpdb/django/templatetags/__init__.py
ircpdb/django/templatetags/ircpdb.py
tests/__init__.py
tests/test_bot.py
tests/test_config.py
tests/test_debugger.py
tests/test_parse.py